trackfs/__init__.py
trackfs/albuminfo.py
trackfs/cuesheet.py
trackfs/flactracks.py
trackfs/fuseops.py
trackfs/fusepath.py
trackfs-0.2.6.dist-info/LICENSE.md
trackfs-0.2.6.dist-info/METADATA
trackfs-0.2.6.dist-info/WHEEL
trackfs-0.2.6.dist-info/entry_points.txt
trackfs-0.2.6.dist-info/top_level.txt
trackfs-0.2.6.dist-info/RECORD
