Metadata-Version: 2.1
Name: trackfs
Version: 0.2.6
Summary: A read-only FUSE filesystem that splits FLAC+CUE files into individual FLAC files per track
Home-page: https://github.com/andresch/trackfs
Author: Andreas Schmidt
Author-email: author@example.com
License: UNKNOWN
Platform: UNKNOWN
Classifier: Programming Language :: Python :: 3
Classifier: Development Status :: 4 - Beta
Classifier: License :: OSI Approved :: GNU Lesser General Public License v3 or later (LGPLv3+)
Classifier: Operating System :: POSIX
Requires-Python: >=3.8
Requires-Dist: mutagen
Requires-Dist: fusepy
Requires-Dist: Lark
Requires-Dist: chardet
